{
  "meta": {
    "id": "336",
    "name": "Palindrome 6",
    "par": 3,
    "intro": "Placeholder puzzle configuration."
  },
  "board": {
    "size": [
      3,
      5
    ],
    "goal": [
      2,
      1
    ],
    "seeds": [
      {
        "text": "X",
        "r": 1,
        "c": 4,
        "dir": "H"
      }
    ],
    "specials": []
  },
  "deck": [
    "R",
    "L",
    "X",
    "F",
    "O",
    "X"
  ],
  "startingHand": [
    "R",
    "L",
    "X",
    "F"
  ],
  "allowedWords": [
    "frf",
    "oxlx",
    "xlxo"
  ],
  "notes": "Autogenerated placeholder content for level 336."
}
